libefiling/__init__.py
libefiling/archive/__init__.py
libefiling/archive/aaa.py
libefiling/archive/extract.py
libefiling/archive/handler.py
libefiling/archive/nnf.py
libefiling/archive/utils.py
libefiling/charset.py
libefiling/cli.py
libefiling/default_config.py
libefiling/image/__init__.py
libefiling/image/convert.py
libefiling/image/kind.py
libefiling/image/mediatype.py
libefiling/image/ocr.py
libefiling/image/params.py
libefiling/image/save_as_xml.py
libefiling/manifest.py
libefiling/parse.py
libefiling-0.1.37.dist-info/METADATA
libefiling-0.1.37.dist-info/WHEEL
libefiling-0.1.37.dist-info/entry_points.txt
libefiling-0.1.37.dist-info/licenses/LICENSE
libefiling-0.1.37.dist-info/RECORD
