Metadata-Version: 2.4
Name: libefiling
Version: 0.1.37
Summary: A Python library for e-filing systems.
License-Expression: MIT
License-File: LICENSE
Keywords: example,testpypi,demo
Author: hyperion13th144m
Author-email: hyperion13th144m@gmail.com
Requires-Python: >=3.12
Classifier: Programming Language :: Python :: 3
Classifier: License :: OSI Approved :: MIT License
Classifier: Operating System :: POSIX :: Linux
Requires-Dist: asn1crypto (>=1.5.1,<2.0.0)
Requires-Dist: dotenv (>=0.9.9,<0.10.0)
Requires-Dist: pillow (>=12.0.0,<13.0.0)
Requires-Dist: pydantic (>=2.12.5,<3.0.0)
Requires-Dist: pytesseract (>=0.3.13,<0.4.0)
Project-URL: Homepage, https://github.com/hyperion13th144m/libefiling
Project-URL: Repository, https://github.com/hyperion13th144m/libefiling
